py_uds_demo/__init__.py
py_uds_demo/__main__.py
py_uds_demo/core/__init__.py
py_uds_demo/core/client.py
py_uds_demo/core/server.py
py_uds_demo/core/utils/__init__.py
py_uds_demo/core/utils/helpers.py
py_uds_demo/core/utils/responses.py
py_uds_demo/core/utils/services/__init__.py
py_uds_demo/core/utils/services/data_transmission.py
py_uds_demo/core/utils/services/diagnostic_and_commmunication_management.py
py_uds_demo/core/utils/services/input_output_contol.py
py_uds_demo/core/utils/services/negative_response.py
py_uds_demo/core/utils/services/remote_activation_of_routine.py
py_uds_demo/core/utils/services/stored_data_transmission.py
py_uds_demo/core/utils/services/upload_download.py
py_uds_demo/interface/__init__.py
py_uds_demo/interface/api.py
py_uds_demo/interface/cli.py
py_uds_demo/interface/gui.py
py_uds_demo/interface/web.py
py_uds_demo-26.0.0.dist-info/WHEEL
py_uds_demo-26.0.0.dist-info/METADATA
py_uds_demo-26.0.0.dist-info/RECORD
