Metadata-Version: 2.3
Name: py-uds-demo
Version: 26.0.0
Summary: Learn and Practice UDS Protocol
Keywords: python,template
Author: chaitu-ycr
Author-email: chaitu-ycr <chaitu.ycr@gmail.com>
License: MIT License
Classifier: Programming Language :: Python :: 3
Classifier: License :: OSI Approved :: MIT License
Classifier: Operating System :: Microsoft :: Windows
Requires-Dist: dearpygui
Requires-Dist: nicegui[native]
Requires-Python: >=3.10, <=3.14
Project-URL: homepage, https://github.com/chaitu-ycr/py-uds-demo
Project-URL: repository, https://github.com/chaitu-ycr/py-uds-demo
Project-URL: documentation, https://chaitu-ycr.github.io/py-uds-demo/
